df1/__init__.py
df1/df1_client.py
df1/file_type.py
df1/sts_codes.py
df1/commands/__init__.py
df1/commands/base_command.py
df1/commands/command_0fa2.py
df1/commands/command_0faa.py
df1/commands/command_0fab.py
df1/commands/command_0fab_single_bit.py
df1/models/__init__.py
df1/models/base_data_frame.py
df1/models/base_frame.py
df1/models/base_plc.py
df1/models/crc16.py
df1/models/df1_plc.py
df1/models/frame_factory.py
df1/models/receive_buffer.py
df1/models/reply_timeout.py
df1/models/tx_symbol.py
df1/models/exceptions/__init__.py
df1/models/exceptions/send_queue_overflow_error.py
df1/models/exceptions/send_receive_error.py
df1/models/exceptions/thread_error.py
df1/replies/__init__.py
df1/replies/base_simple_reply.py
df1/replies/reply_4f.py
df1/replies/reply_ack.py
df1/replies/reply_enq.py
df1/replies/reply_nak.py
df1-0.5.dist-info/METADATA
df1-0.5.dist-info/RECORD
df1-0.5.dist-info/WHEEL
df1-0.5.dist-info/top_level.txt
