Metadata-Version: 2.1
Name: df1
Version: 0.5
Summary: A basic DF1 implementation in Python
Home-page: UNKNOWN
Author: Jerther
Author-email: jtheriault@metalsartigan.com
License: MIT License
Platform: UNKNOWN
